{
    "content": [
        "3859c2b3513986300c56b6d9ae0f8162\t{\"Parent\":\"DefaultProperties\",\"Comment\":\"fastbot crawler\",\"Browser\":\"fastbot crawler\",\"Browser_Type\":\"Bot\\\/Crawler\",\"Browser_Maker\":\"Pagedesign GmbH\",\"Beta\":true,\"Crawler\":true}",
        "38522fb193580b412e7b94c4d127d7ff\t{\"Parent\":\"Brave Generic\",\"Browser_Bits\":\"32\",\"Platform\":\"WinVista\",\"Platform_Version\":\"6.0\",\"Platform_Description\":\"Windows Vista\",\"Platform_Bits\":\"32\",\"Platform_Maker\":\"Microsoft Corporation\",\"Win32\":true,\"Device_Name\":\"Windows Desktop\",\"Device_Code_Name\":\"Windows Desktop\"}",
        "385640a6bf20baf115060db02f1c5764\t{\"Parent\":\"UC Browser 9.7\",\"Platform_Version\":\"4.2\",\"isTablet\":true,\"Device_Name\":\"Galaxy Note 10.1 3G \\u0026 WiFi\",\"Device_Maker\":\"Samsung\",\"Device_Type\":\"Tablet\",\"Device_Code_Name\":\"GT-N8000\",\"Device_Brand_Name\":\"Samsung\",\"RenderingEngine_Name\":\"U2\",\"RenderingEngine_Description\":\"a WebKit Fork by UC Web\",\"RenderingEngine_Maker\":\"UCWeb Inc.\"}",
        "385ae319cedcb2d40728764a87dd9ef2\t{\"Parent\":\"Comodo Dragon 44.2\",\"Browser_Bits\":\"64\",\"Platform\":\"Win10\",\"Platform_Version\":\"10.0\",\"Platform_Description\":\"Windows 10\",\"Platform_Bits\":\"64\",\"Platform_Maker\":\"Microsoft Corporation\",\"Win64\":true,\"Device_Name\":\"Windows Desktop\",\"Device_Code_Name\":\"Windows Desktop\"}",
        "3851b561ea74c8622ae15e0084b9e844\t{\"Parent\":\"Comodo Dragon 18.1\",\"Browser_Bits\":\"64\",\"Platform\":\"Win8.1\",\"Platform_Version\":\"6.3\",\"Platform_Description\":\"Windows 8.1\",\"Platform_Bits\":\"64\",\"Platform_Maker\":\"Microsoft Corporation\",\"Win64\":true,\"Device_Name\":\"Windows Desktop\",\"Device_Code_Name\":\"Windows Desktop\"}",
        "385af5e05094dbbd2f8028b0bd560dd0\t{\"Parent\":\"Android WebView 5.0\",\"Platform_Version\":\"4.4\",\"Device_Name\":\"Ascend P6\",\"Device_Maker\":\"Huawei\",\"Device_Code_Name\":\"P6-U06\",\"Device_Brand_Name\":\"Huawei\"}",
        "3857ec0d6d55d57f872924ab85af7496\t{\"Parent\":\"Android WebView 4.4\",\"Platform_Version\":\"2.2\",\"isMobileDevice\":false,\"Device_Name\":\"NBPC724\",\"Device_Maker\":\"Coby\",\"Device_Type\":\"Desktop\",\"Device_Pointing_Method\":\"mouse\",\"Device_Code_Name\":\"NBPC724\",\"Device_Brand_Name\":\"Coby\"}",
        "385b3afe10ca276ee5a06416e5941cc1\t{\"Parent\":\"Android WebView 4.1\",\"Platform_Version\":\"4.4\",\"isTablet\":true,\"Device_Name\":\"Galaxy Tab 4 10.1 LTE\",\"Device_Maker\":\"Samsung\",\"Device_Type\":\"Tablet\",\"Device_Code_Name\":\"SM-T535\",\"Device_Brand_Name\":\"Samsung\"}",
        "385b4e5dd72881539df3dfc8609c3ab6\t{\"Parent\":\"Android WebView 1.5\",\"Platform_Version\":\"2.3\",\"Device_Name\":\"Galaxy Ace 2\",\"Device_Maker\":\"Samsung\",\"Device_Code_Name\":\"GT-I8160\",\"Device_Brand_Name\":\"Samsung\"}",
        "385fc05b64658ef91c8cb533b6a3118c\t{\"Parent\":\"Android WebView 1.5\",\"Platform_Version\":\"4.1\",\"Device_Name\":\"Galaxy S II NFC\",\"Device_Maker\":\"Samsung\",\"Device_Code_Name\":\"GT-I9105P\",\"Device_Brand_Name\":\"Samsung\"}",
        "3859fb96d8d540e95404362d2ca58357\t{\"Parent\":\"Opera Mobile 21.0 for Android\",\"Platform_Version\":\"4.1\",\"Device_Name\":\"A706\",\"Device_Maker\":\"Lenovo\",\"Device_Code_Name\":\"A706\",\"Device_Brand_Name\":\"Lenovo\"}",
        "38550b6db6e96af3aa6de19a7be8855c\t{\"Parent\":\"Opera 6.03\",\"Browser_Bits\":\"32\",\"Platform\":\"MacOSX\",\"Platform_Version\":\"10.5\",\"Platform_Description\":\"Mac OS X\",\"Platform_Bits\":\"32\",\"Platform_Maker\":\"Apple Inc\",\"Device_Name\":\"Macintosh\",\"Device_Maker\":\"Apple Inc\",\"Device_Code_Name\":\"Macintosh\",\"Device_Brand_Name\":\"Apple\"}",
        "38504327b5326176249e88dfaa8e39a5\t{\"Parent\":\"Chrome 50.0 for Android\",\"Platform_Version\":\"4.1\",\"Device_Name\":\"XT925\",\"Device_Maker\":\"Motorola\",\"Device_Pointing_Method\":\"unknown\",\"Device_Code_Name\":\"XT925\",\"Device_Brand_Name\":\"Motorola\"}",
        "385e7b7099edb9ef3ad60258dcf736b5\t{\"Parent\":\"Chrome 49.0 for Android\",\"Platform_Version\":\"4.1\",\"isTablet\":true,\"Device_Name\":\"101 G10\",\"Device_Maker\":\"Archos\",\"Device_Type\":\"Tablet\",\"Device_Code_Name\":\"101 G10\",\"Device_Brand_Name\":\"Archos\"}",
        "385a9335ff7edad9c35f8dfab01ce039\t{\"Parent\":\"Chrome 45.0 for Android\",\"Platform_Version\":\"4.3\",\"Device_Name\":\"Xperia V\",\"Device_Maker\":\"Sony\",\"Device_Code_Name\":\"LT25i\",\"Device_Brand_Name\":\"Sony\"}",
        "3858a44525f492c3ed6c96f1bea23149\t{\"Parent\":\"Chrome 43.0 for Android\",\"Platform_Version\":\"4.2\",\"Device_Name\":\"One X+\",\"Device_Maker\":\"HTC\",\"Device_Code_Name\":\"PM63100\",\"Device_Brand_Name\":\"HTC\"}",
        "385baf0db5dd0458c1a06cd6d426ad89\t{\"Parent\":\"Chrome 40.0 for Android\",\"Platform_Version\":\"4.2\",\"Device_Name\":\"Live\",\"Device_Maker\":\"SonyEricsson\",\"Device_Code_Name\":\"WT19i\",\"Device_Brand_Name\":\"SonyEricsson\"}",
        "385bd800881605a189840d98320d2d4d\t{\"Parent\":\"Chrome 36.0 for Android\",\"Platform_Version\":\"4.4\",\"Device_Name\":\"Galaxy Pocket Neo\",\"Device_Maker\":\"Samsung\",\"Device_Code_Name\":\"GT-S5310M\",\"Device_Brand_Name\":\"Samsung\"}",
        "3857aecff87a8b1be16124e920e35407\t{\"Parent\":\"Chrome 33.0 for Android\",\"Platform_Version\":\"4.4\",\"Device_Name\":\"Galaxy S III\",\"Device_Maker\":\"Samsung\",\"Device_Code_Name\":\"GT-I9300\",\"Device_Brand_Name\":\"Samsung\"}",
        "3856ba985793f5d45724c9a98bd1bb0a\t{\"Parent\":\"Chrome 19.0 for iOS\",\"Platform_Version\":\"6.0\",\"isTablet\":true,\"Device_Name\":\"iPad\",\"Device_Type\":\"Tablet\",\"Device_Code_Name\":\"iPad\"}",
        "38535c407a58eca072c2218457a754bf\t{\"Parent\":\"Microsoft Office 2013\",\"Browser_Bits\":\"64\",\"Platform\":\"WinVista\",\"Platform_Version\":\"6.0\",\"Platform_Description\":\"Windows Vista\",\"Platform_Bits\":\"64\",\"Platform_Maker\":\"Microsoft Corporation\",\"Win64\":true,\"RenderingEngine_Version\":\"4.0\"}",
        "3852cdd46388c9502cc7022a3d31fc62\t{\"Parent\":\"Android Browser 4.0\",\"Platform_Version\":\"4.2\",\"Device_Name\":\"Optimus L7\",\"Device_Maker\":\"LG\",\"Device_Pointing_Method\":\"unknown\",\"Device_Code_Name\":\"P700\",\"Device_Brand_Name\":\"LG\"}",
        "385f8afd6aac1ff16d7ab8e586be132f\t{\"Parent\":\"Atomic Browser 5.1\",\"Platform_Version\":\"6.0\"}",
        "38590fd842013aa30bb8afb24c70f5cc\t{\"Parent\":\"BlackBerry 4.1\",\"Device_Name\":\"BlackBerry 8700c\",\"Device_Code_Name\":\"BlackBerry 8700c\"}",
        "38516617e2d775caa668ab4f2e59b7ed\t{\"Parent\":\"Firefox 37.0\",\"Browser_Bits\":\"32\",\"Platform\":\"Win8.1\",\"Platform_Version\":\"6.3\",\"Platform_Description\":\"Windows 8.1\",\"Platform_Bits\":\"32\",\"Platform_Maker\":\"Microsoft Corporation\",\"Win32\":true,\"Device_Name\":\"Windows Desktop\",\"Device_Code_Name\":\"Windows Desktop\"}",
        "3856a54c4e2c64f9cf19ba4f3afaaed3\t{\"Parent\":\"Klondike\"}",
        "385e2789fe815792eab4c45f676d9e29\t{\"Parent\":\"Mitsu\"}"
    ]
}