{
    "content": [
        "16dc3d136220c6af840bc9b646c6a909\t{\"Parent\":\"UC Browser 9.8\",\"Platform_Version\":\"4.0\",\"Device_Name\":\"Grand Era\",\"Device_Maker\":\"ZTE\",\"Device_Code_Name\":\"Grand Era\",\"Device_Brand_Name\":\"ZTE\",\"RenderingEngine_Name\":\"U2\",\"RenderingEngine_Description\":\"a WebKit Fork by UC Web\",\"RenderingEngine_Maker\":\"UC Web\"}",
        "16d12b55b27d5276c3320dd7a284d7b6\t{\"Parent\":\"UC Browser 9.4\",\"Platform\":\"JAVA\",\"Platform_Maker\":\"Oracle\",\"Device_Name\":\"205\",\"Device_Maker\":\"Nokia\",\"Device_Pointing_Method\":\"unknown\",\"Device_Code_Name\":\"205\",\"Device_Brand_Name\":\"Nokia\",\"RenderingEngine_Name\":\"U2\",\"RenderingEngine_Description\":\"a WebKit Fork by UC Web\",\"RenderingEngine_Maker\":\"UC Web\"}",
        "16dd6d45c66ffbf6f18296db74ee35d0\t{\"Parent\":\"Avant\\\/IE 8.0\",\"Browser_Bits\":\"32\",\"Platform\":\"WinVista\",\"Platform_Version\":\"6.0\",\"Platform_Description\":\"Windows Vista\",\"Platform_Bits\":\"64\",\"Platform_Maker\":\"Microsoft Corporation\",\"Win64\":true}",
        "16d696bcc3d4f932ea98011a4d60ca91\t{\"Parent\":\"Facebook App 26.0 for iOS\",\"Platform_Version\":\"6.1\",\"isTablet\":true,\"Device_Name\":\"iPad\",\"Device_Type\":\"Tablet\",\"Device_Code_Name\":\"iPad\"}",
        "16dea0c5b79bf396430a0f989f35b1a1\t{\"Parent\":\"Facebook App 16.0 for Android\",\"Platform_Version\":\"4.2\",\"JavaApplets\":true,\"Device_Name\":\"Trooper X40\",\"Device_Maker\":\"KAZAM\",\"Device_Code_Name\":\"Trooper X40\",\"Device_Brand_Name\":\"KAZAM\",\"RenderingEngine_Name\":\"WebKit\",\"RenderingEngine_Description\":\"For Google Chrome, iOS (including both mobile Safari, WebViews within third-party apps, and web clips), Safari, Arora, Midori, OmniWeb, Shiira, iCab since version 4, Web, SRWare Iron, Rekonq, and in Maxthon 3.\",\"RenderingEngine_Maker\":\"Apple Inc\"}",
        "16d3c8c3f024702f91068e14592ea5b8\t{\"Parent\":\"Facebook App 5.4 for Android\",\"Platform_Version\":\"4.2\",\"JavaApplets\":true,\"Device_Name\":\"Honor 3X\",\"Device_Maker\":\"Huawei\",\"Device_Code_Name\":\"G750-T00\",\"Device_Brand_Name\":\"Huawei\",\"RenderingEngine_Name\":\"WebKit\",\"RenderingEngine_Description\":\"For Google Chrome, iOS (including both mobile Safari, WebViews within third-party apps, and web clips), Safari, Arora, Midori, OmniWeb, Shiira, iCab since version 4, Web, SRWare Iron, Rekonq, and in Maxthon 3.\",\"RenderingEngine_Maker\":\"Apple Inc\"}",
        "16da5d34f63ffc0e506558aa2c996f53\t{\"Parent\":\"Facebook App 4.1 for Android\",\"Platform_Version\":\"4.2\",\"JavaApplets\":true,\"Device_Name\":\"Desire 601\",\"Device_Maker\":\"HTC\",\"Device_Code_Name\":\"Desire 601\",\"Device_Brand_Name\":\"HTC\",\"RenderingEngine_Name\":\"WebKit\",\"RenderingEngine_Description\":\"For Google Chrome, iOS (including both mobile Safari, WebViews within third-party apps, and web clips), Safari, Arora, Midori, OmniWeb, Shiira, iCab since version 4, Web, SRWare Iron, Rekonq, and in Maxthon 3.\",\"RenderingEngine_Maker\":\"Apple Inc\"}",
        "16d9987dbf252920bf30d3b1f37793c3\t{\"Parent\":\"Facebook App 1.8 for Android\",\"Platform_Version\":\"4.4\",\"Device_Name\":\"Find 5\",\"Device_Maker\":\"OPPO\",\"Device_Code_Name\":\"X909\",\"Device_Brand_Name\":\"OPPO\"}",
        "16dad88c487f383e0c0485ce277cdbfb\t{\"Parent\":\"Comodo Dragon 35.0\",\"Platform\":\"WinXP\",\"Platform_Version\":\"5.2\",\"Platform_Description\":\"Windows XP\",\"Platform_Maker\":\"Microsoft Corporation\",\"Win32\":true,\"Device_Name\":\"Windows Desktop\",\"Device_Code_Name\":\"Windows Desktop\"}",
        "16d249fb924d5c00ce7bcbecbbdf8f8f\t{\"Parent\":\"Android WebView 4.3\",\"Platform_Version\":\"4.4\",\"Device_Name\":\"A328t\",\"Device_Maker\":\"Lenovo\",\"Device_Code_Name\":\"A328t\",\"Device_Brand_Name\":\"Lenovo\"}",
        "16d53fe6a289955a253b934955567393\t{\"Parent\":\"Android WebView 4.1\",\"Platform_Version\":\"2.3\",\"Device_Name\":\"Galaxy Ace\",\"Device_Maker\":\"Samsung\",\"Device_Pointing_Method\":\"unknown\",\"Device_Code_Name\":\"GT-S5839i\",\"Device_Brand_Name\":\"Samsung\"}",
        "16d088ef8bb964ac6a2335c3a2c6d916\t{\"Parent\":\"Android WebView 4.1\",\"Platform_Version\":\"4.1\",\"Device_Name\":\"Xperia Arc\",\"Device_Maker\":\"SonyEricsson\",\"Device_Code_Name\":\"LT18i\",\"Device_Brand_Name\":\"SonyEricsson\"}",
        "16d33275997f8217a726df34f3d09f3c\t{\"Parent\":\"Android WebView 1.6\",\"Platform_Version\":\"4.1\",\"Device_Name\":\"Xperia miro\",\"Device_Maker\":\"Sony\",\"Device_Code_Name\":\"ST23i\",\"Device_Brand_Name\":\"Sony\"}",
        "16d6b6af81efa20c41c77126fd22b20e\t{\"Parent\":\"Opera 12.13\",\"Browser_Bits\":\"32\",\"Platform\":\"MacOSX\",\"Platform_Version\":\"10.6\",\"Platform_Description\":\"Mac OS X\",\"Platform_Bits\":\"32\",\"Platform_Maker\":\"Apple Inc\",\"Device_Name\":\"Macintosh\",\"Device_Maker\":\"Apple Inc\",\"Device_Code_Name\":\"Macintosh\",\"Device_Brand_Name\":\"Apple\"}",
        "16db8fe8278e02269b2a76413973c0cc\t{\"Parent\":\"Opera 9.02\",\"Browser_Bits\":\"32\",\"Platform\":\"WinME\",\"Platform_Version\":\"ME\",\"Platform_Description\":\"Windows ME\",\"Platform_Bits\":\"32\",\"Platform_Maker\":\"Microsoft Corporation\",\"Win32\":true,\"Device_Name\":\"Windows Desktop\",\"Device_Code_Name\":\"Windows Desktop\"}",
        "16dab7d0f6a460c7f47f4122bc7c0eb0\t{\"Parent\":\"Opera 8.51\",\"Browser_Bits\":\"32\",\"Platform\":\"WinNT\",\"Platform_Version\":\"4.0\",\"Platform_Description\":\"Windows NT\",\"Platform_Bits\":\"32\",\"Platform_Maker\":\"Microsoft Corporation\",\"Win32\":true,\"Device_Name\":\"Windows Desktop\",\"Device_Code_Name\":\"Windows Desktop\"}",
        "16d9975ebededefea8472f0580457477\t{\"Parent\":\"Opera 7.22\",\"Browser_Bits\":\"32\",\"Platform\":\"FreeBSD\",\"Platform_Description\":\"FreeBSD\",\"Platform_Bits\":\"32\",\"Platform_Maker\":\"FreeBSD Foundation\"}",
        "16d35d398ac5699240ec472eaf58eb36\t{\"Parent\":\"Silk 3.58\",\"Platform_Version\":\"4.0\",\"isTablet\":true,\"Device_Name\":\"Kindle Fire 7\",\"Device_Type\":\"Tablet\",\"Device_Code_Name\":\"KFOT\"}",
        "16d49a43e43b673a69122b8ba72d4e29\t{\"Parent\":\"DefaultProperties\",\"Comment\":\"Midori 0.1\",\"Browser\":\"Midori\",\"Browser_Type\":\"Browser\",\"Browser_Maker\":\"Christian Dywan\",\"Version\":\"0.1\",\"MinorVer\":\"1\",\"Frames\":true,\"IFrames\":true,\"Tables\":true,\"Cookies\":true,\"JavaScript\":true,\"JavaApplets\":true,\"CssVersion\":\"2\",\"Device_Name\":\"general Desktop\",\"Device_Maker\":\"Various\",\"Device_Type\":\"Desktop\",\"Device_Pointing_Method\":\"mouse\",\"Device_Code_Name\":\"general Desktop\",\"RenderingEngine_Name\":\"WebKit\",\"RenderingEngine_Description\":\"For Google Chrome, iOS (including both mobile Safari, WebViews within third-party apps, and web clips), Safari, Arora, Midori, OmniWeb, Shiira, iCab since version 4, Web, SRWare Iron, Rekonq, and in Maxthon 3.\",\"RenderingEngine_Maker\":\"Apple Inc\"}",
        "16d65cbf22d93a414a797e7f2d470c7c\t{\"Parent\":\"Chrome 48.0\",\"Browser_Bits\":\"32\",\"Platform\":\"Win7\",\"Platform_Version\":\"6.1\",\"Platform_Description\":\"Windows 7\",\"Platform_Bits\":\"32\",\"Platform_Maker\":\"Microsoft Corporation\",\"Win32\":true,\"Device_Name\":\"Windows Desktop\",\"Device_Code_Name\":\"Windows Desktop\"}",
        "16d5ae215c530567329393ba0e00331b\t{\"Parent\":\"Chrome 47.0 for Android\",\"Platform_Version\":\"4.1\",\"Device_Name\":\"Galaxy S4\",\"Device_Maker\":\"Samsung\",\"Device_Code_Name\":\"GT-I9500\",\"Device_Brand_Name\":\"Samsung\"}",
        "16dc0c2c4c52db71111569fb0482b6bc\t{\"Parent\":\"Chrome 47.0 for Android\",\"Platform_Version\":\"4.2\",\"isTablet\":true,\"Device_Name\":\"GU7814\",\"Device_Maker\":\"Globex\",\"Device_Type\":\"Tablet\",\"Device_Code_Name\":\"GU7814\",\"Device_Brand_Name\":\"Globex\"}",
        "16d60aa6c7631f4d4c55d54251dff543\t{\"Parent\":\"Chrome 46.0 for Android\",\"Platform_Version\":\"4.0\",\"Device_Name\":\"One S\",\"Device_Maker\":\"HTC\",\"Device_Code_Name\":\"PJ401\",\"Device_Brand_Name\":\"HTC\"}",
        "16dfb15002d6be8ac6679e878b6f960d\t{\"Parent\":\"Chrome 46.0 for Android\",\"Platform_Version\":\"4.3\",\"Device_Name\":\"Nexus S\",\"Device_Maker\":\"Samsung\",\"Device_Code_Name\":\"Nexus S\",\"Device_Brand_Name\":\"Google\"}",
        "16d09ec97c3910b6c340d32eb4b94a9a\t{\"Parent\":\"Chrome 40.0\",\"Browser_Bits\":\"32\",\"Platform\":\"WinVista\",\"Platform_Version\":\"6.0\",\"Platform_Description\":\"Windows Vista\",\"Platform_Bits\":\"32\",\"Platform_Maker\":\"Microsoft Corporation\",\"Win32\":true,\"Device_Name\":\"Windows Desktop\",\"Device_Code_Name\":\"Windows Desktop\"}",
        "16d162b395b070fcb218499f4398aa81\t{\"Parent\":\"Chrome 39.0 for Android\",\"Platform_Version\":\"4.2\",\"Device_Name\":\"Galaxy S II NFC\",\"Device_Maker\":\"Samsung\",\"Device_Code_Name\":\"GT-I9105P\",\"Device_Brand_Name\":\"Samsung\"}",
        "16d6c488d9906459d7e18dcf39d377e6\t{\"Parent\":\"Chrome 36.0 for iOS\",\"Platform_Version\":\"5.1\"}",
        "16def5bdcabdee11f7abd5ac5e9f0841\t{\"Parent\":\"Chrome 35.0 for Android\",\"Platform_Version\":\"4.3\",\"Device_Name\":\"Galaxy Note 3 3G\",\"Device_Maker\":\"Samsung\",\"Device_Code_Name\":\"SM-N900\",\"Device_Brand_Name\":\"Samsung\"}",
        "16d53725fd6b76a5c1d3da4d903ea3b5\t{\"Parent\":\"OneBrowser 3.1\",\"Browser_Bits\":\"32\",\"Platform\":\"Android\",\"Platform_Version\":\"4.2\",\"Platform_Description\":\"Android OS\",\"Platform_Bits\":\"32\",\"Platform_Maker\":\"Google Inc\"}",
        "16d356e4b725d5d580b000dff8bc487d\t{\"Parent\":\"iBrowser 2.8\",\"Browser_Bits\":\"32\",\"Platform\":\"Android\",\"Platform_Version\":\"4.4\",\"Platform_Description\":\"Android OS\",\"Platform_Bits\":\"32\",\"Platform_Maker\":\"Google Inc\"}",
        "16d7a146c0daa31ba8c0c60e1eeb7d49\t{\"Parent\":\"QupZilla 1.5\",\"Browser_Bits\":\"32\",\"Platform\":\"Win10\",\"Platform_Version\":\"6.4\",\"Platform_Description\":\"Windows 10\",\"Platform_Bits\":\"32\",\"Platform_Maker\":\"Microsoft Corporation\",\"Win32\":true,\"Device_Name\":\"Windows Desktop\",\"Device_Code_Name\":\"Windows Desktop\"}",
        "16d576e4df5a8a1140a2012ce67e09c2\t{\"Parent\":\"Android Browser 4.0\",\"Platform_Version\":\"2.2\",\"Device_Name\":\"XPRT (CDMA)\",\"Device_Maker\":\"Motorola\",\"Device_Code_Name\":\"MB612\",\"Device_Brand_Name\":\"Motorola\"}",
        "16db73c20d66eac1fa9eac34b18b0dff\t{\"Parent\":\"Lunascape 6.6\",\"Browser_Bits\":\"32\",\"Platform\":\"WinVista\",\"Platform_Version\":\"6.0\",\"Platform_Description\":\"Windows Vista\",\"Platform_Bits\":\"32\",\"Platform_Maker\":\"Microsoft Corporation\",\"Win32\":true,\"JavaApplets\":true,\"Device_Name\":\"Windows Desktop\",\"Device_Code_Name\":\"Windows Desktop\",\"RenderingEngine_Name\":\"WebKit\",\"RenderingEngine_Description\":\"For Google Chrome, iOS (including both mobile Safari, WebViews within third-party apps, and web clips), Safari, Arora, Midori, OmniWeb, Shiira, iCab since version 4, Web, SRWare Iron, Rekonq, and in Maxthon 3.\",\"RenderingEngine_Maker\":\"Apple Inc\"}",
        "16d89fd192968a7223459af2547440c7\t{\"Parent\":\"Firefox 36.0\",\"Browser_Bits\":\"32\",\"Platform\":\"WinXP\",\"Platform_Version\":\"5.1\",\"Platform_Description\":\"Windows XP\",\"Platform_Bits\":\"64\",\"Platform_Maker\":\"Microsoft Corporation\",\"Win64\":true,\"Device_Name\":\"Windows Desktop\",\"Device_Code_Name\":\"Windows Desktop\"}",
        "16dda607e6079fa9c31f5c39cf9930ee\t{\"Parent\":\"Firefox 16.0\",\"Browser_Bits\":\"32\",\"Platform\":\"Win8.1\",\"Platform_Version\":\"6.3\",\"Platform_Description\":\"Windows 8.1\",\"Platform_Bits\":\"32\",\"Platform_Maker\":\"Microsoft Corporation\",\"Win32\":true,\"Device_Name\":\"Windows Desktop\",\"Device_Code_Name\":\"Windows Desktop\"}",
        "16d136210b87ef6251c60351abe66e6e\t{\"Parent\":\"Firefox 8.0\",\"Browser_Bits\":\"32\",\"Platform\":\"Ubuntu\",\"Platform_Description\":\"Ubuntu Linux\",\"Platform_Bits\":\"32\",\"Platform_Maker\":\"Canonical Foundation\",\"Device_Name\":\"Linux Desktop\",\"Device_Code_Name\":\"Linux Desktop\"}"
    ]
}