{
    "content": [
        "57d946e116cbd4198d4a3ded75deaf29\t{\"Parent\":\"DefaultProperties\",\"Comment\":\"Chromium 31.0\",\"Browser\":\"Chromium\",\"Browser_Type\":\"Browser\",\"Browser_Bits\":\"32\",\"Browser_Maker\":\"Google Inc\",\"Version\":\"31.0\",\"MajorVer\":\"31\",\"Platform\":\"Linux\",\"Platform_Description\":\"Linux\",\"Platform_Bits\":\"32\",\"Platform_Maker\":\"Linux Foundation\",\"Frames\":true,\"IFrames\":true,\"Tables\":true,\"Cookies\":true,\"JavaScript\":true,\"CssVersion\":\"3\",\"Device_Name\":\"Linux Desktop\",\"Device_Maker\":\"Various\",\"Device_Type\":\"Desktop\",\"Device_Pointing_Method\":\"mouse\",\"Device_Code_Name\":\"Linux Desktop\",\"RenderingEngine_Name\":\"Blink\",\"RenderingEngine_Description\":\"a WebKit Fork by Google\",\"RenderingEngine_Maker\":\"Google Inc\"}",
        "57dead9622361c2f8a3d046ac5a07488\t{\"Parent\":\"UC Browser 10.4\",\"Platform_Version\":\"4.2\",\"Device_Name\":\"Blade L2\",\"Device_Maker\":\"ZTE\",\"Device_Code_Name\":\"Blade L2\",\"Device_Brand_Name\":\"ZTE\"}",
        "57db2779074ccca393ec826bdde0efc5\t{\"Parent\":\"UC Browser 10.4\",\"Platform_Version\":\"5.0\",\"Device_Name\":\"Galaxy Note\",\"Device_Maker\":\"Samsung\",\"Device_Code_Name\":\"GT-N7000\",\"Device_Brand_Name\":\"Samsung\"}",
        "57d3e5cdb28ae1b4a48e0531dcea95a2\t{\"Parent\":\"Facebook App 35.0 for Android\",\"Platform_Version\":\"4.4\",\"Device_Name\":\"A606\",\"Device_Maker\":\"Lenovo\",\"Device_Code_Name\":\"A606\",\"Device_Brand_Name\":\"Lenovo\"}",
        "57d2b7c1b6f671c46d127767e26c10c5\t{\"Parent\":\"Facebook App 29.0 for iOS\",\"Platform_Version\":\"7.1\",\"Device_Name\":\"iPhone\",\"Device_Type\":\"Mobile Phone\",\"Device_Code_Name\":\"iPhone\"}",
        "57d94f3c8482fe9805e310a74ea20a8d\t{\"Parent\":\"Facebook App 14.8 for iOS\",\"Device_Name\":\"iPhone\",\"Device_Type\":\"Mobile Phone\",\"Device_Code_Name\":\"iPhone\"}",
        "57db2318bf843c8ebded9d732e23c870\t{\"Parent\":\"Facebook App 14.0 for iOS\",\"Platform_Version\":\"3.2\",\"Device_Name\":\"iPhone\",\"Device_Type\":\"Mobile Phone\",\"Device_Code_Name\":\"iPhone\"}",
        "57d59a24efeb4d9106898248e2e088e2\t{\"Parent\":\"Facebook App 10.0 for iOS\",\"Platform_Version\":\"7.1\",\"Device_Name\":\"iPhone\",\"Device_Type\":\"Mobile Phone\",\"Device_Code_Name\":\"iPhone\"}",
        "57d631c4337c394af6895ccfb8b6e83a\t{\"Parent\":\"Facebook App 6.3 for iOS\",\"Device_Name\":\"iPod Touch\",\"Device_Code_Name\":\"iPod Touch\"}",
        "57df088a1f442c86ba52b928bbfce228\t{\"Parent\":\"Facebook App 6.1 for iOS\",\"Platform_Version\":\"5.0\"}",
        "57d237cda497ffa737653d08ac904bcf\t{\"Parent\":\"Facebook App 3.1 for iOS\",\"Platform_Version\":\"6.1\",\"isTablet\":true,\"Device_Name\":\"iPad\",\"Device_Type\":\"Tablet\",\"Device_Code_Name\":\"iPad\"}",
        "57da4081fa508472d3851145c66b5923\t{\"Parent\":\"Facebook App 2.2 for Android\",\"Platform_Version\":\"4.2\",\"JavaApplets\":true,\"Device_Name\":\"P780\",\"Device_Maker\":\"Lenovo\",\"Device_Code_Name\":\"P780\",\"Device_Brand_Name\":\"Lenovo\",\"RenderingEngine_Name\":\"WebKit\",\"RenderingEngine_Description\":\"For Google Chrome, iOS (including both mobile Safari, WebViews within third-party apps, and web clips), Safari, Arora, Midori, OmniWeb, Shiira, iCab since version 4, Web, SRWare Iron, Rekonq, and in Maxthon 3.\",\"RenderingEngine_Maker\":\"Apple Inc\"}",
        "57df685fc8a8cc1cf72f1b96001b758d\t{\"Parent\":\"Comodo Dragon 44.2\",\"Browser_Bits\":\"64\",\"Platform\":\"Win8\",\"Platform_Version\":\"6.2\",\"Platform_Description\":\"Windows 8\",\"Platform_Bits\":\"64\",\"Platform_Maker\":\"Microsoft Corporation\",\"Win64\":true,\"Device_Name\":\"Windows Desktop\",\"Device_Code_Name\":\"Windows Desktop\"}",
        "57d9ef892c0c06bda94450ef4933dc79\t{\"Parent\":\"Android WebView 4.1\",\"Platform_Version\":\"2.3\",\"isTablet\":true,\"Device_Name\":\"Touchlet X7G\",\"Device_Maker\":\"Pearl\",\"Device_Type\":\"Tablet\",\"Device_Code_Name\":\"Touchlet X7G\",\"Device_Brand_Name\":\"Pearl\"}",
        "57d99d8bf5da765308f4c9ae7c221101\t{\"Parent\":\"Android WebView 4.0\",\"Platform_Version\":\"4.1\",\"isTablet\":true,\"Device_Name\":\"Galaxy Tab 10.1\",\"Device_Maker\":\"Samsung\",\"Device_Type\":\"Tablet\",\"Device_Code_Name\":\"GT-P7500\",\"Device_Brand_Name\":\"Samsung\"}",
        "57ddb472dc135136f3a2866ff9cd66ea\t{\"Parent\":\"Android WebView 4.0\",\"Platform_Version\":\"4.1\",\"Device_Name\":\"Galaxy S4\",\"Device_Maker\":\"Samsung\",\"Device_Code_Name\":\"GT-I9505\",\"Device_Brand_Name\":\"Samsung\"}",
        "57d27500ca708aeb75076b0b0ecf2fa0\t{\"Parent\":\"Android WebView 4.0\",\"Platform_Version\":\"4.4\",\"Device_Name\":\"ERA Life 4\",\"Device_Maker\":\"Fly\",\"Device_Code_Name\":\"IQ4409 Quad\",\"Device_Brand_Name\":\"Fly\"}",
        "57dd679b41e997973186e22ca2f2765d\t{\"Parent\":\"Opera Mobile 34.0 for Android\",\"Platform_Version\":\"4.1\",\"Device_Name\":\"Galaxy S III Mini\",\"Device_Maker\":\"Samsung\",\"Device_Code_Name\":\"GT-I8190\",\"Device_Brand_Name\":\"Samsung\"}",
        "57d55a09a2d004b84e4a9864cee6e8a3\t{\"Parent\":\"Opera Mobile 15.0 for Android\",\"Platform_Version\":\"4.1\",\"Device_Name\":\"Galaxy S III Mini\",\"Device_Maker\":\"Samsung\",\"Device_Code_Name\":\"GT-I8190\",\"Device_Brand_Name\":\"Samsung\"}",
        "57d58821fca176669e3f6308baf05cce\t{\"Parent\":\"Opera 12.10\",\"Browser_Bits\":\"32\",\"Platform\":\"MacOSX\",\"Platform_Version\":\"10.7\",\"Platform_Description\":\"Mac OS X\",\"Platform_Bits\":\"32\",\"Platform_Maker\":\"Apple Inc\",\"Device_Name\":\"Macintosh\",\"Device_Maker\":\"Apple Inc\",\"Device_Code_Name\":\"Macintosh\",\"Device_Brand_Name\":\"Apple\"}",
        "57d9a8d6f191a5d6ed1e6806567b1eb3\t{\"Parent\":\"Iron 12.0\",\"Browser_Bits\":\"32\",\"Platform\":\"WinXP\",\"Platform_Version\":\"5.1\",\"Platform_Description\":\"Windows XP\",\"Platform_Bits\":\"64\",\"Platform_Maker\":\"Microsoft Corporation\",\"Win64\":true,\"Device_Name\":\"Windows Desktop\",\"Device_Code_Name\":\"Windows Desktop\"}",
        "57da8dbf0c7a4b75f336d9861e18bbee\t{\"Parent\":\"Silk 3.65\",\"Platform_Version\":\"4.2\",\"isTablet\":true,\"Device_Name\":\"Kindle Fire HDX 7\",\"Device_Type\":\"Tablet\",\"Device_Code_Name\":\"KFTHWI\"}",
        "57dc02b18fcad6dc0817310cb0165e9b\t{\"Parent\":\"Chrome 41.0 for Android\",\"Platform_Version\":\"4.2\",\"isTablet\":true,\"Device_Name\":\"Ideatab A8-50 WI-FI\",\"Device_Maker\":\"Lenovo\",\"Device_Type\":\"Tablet\",\"Device_Code_Name\":\"A5500-F\",\"Device_Brand_Name\":\"Lenovo\"}",
        "57dcf62c2de4158129b2c7311cc5cb67\t{\"Parent\":\"Chrome 40.0 for Android\",\"Platform_Version\":\"4.4\",\"Device_Name\":\"Optimus L9 II\",\"Device_Maker\":\"LG\",\"Device_Code_Name\":\"D605\",\"Device_Brand_Name\":\"LG\"}",
        "57d8a72e65091adbe47e1b63d93092c5\t{\"Parent\":\"Chrome 35.0 for Android\",\"Platform_Version\":\"4.2\",\"isTablet\":true,\"Device_Name\":\"Galaxy Tab 3 Lite 7\",\"Device_Maker\":\"Samsung\",\"Device_Type\":\"Tablet\",\"Device_Code_Name\":\"SM-T110\",\"Device_Brand_Name\":\"Samsung\"}",
        "57d381f81be08b65d05970b95fdb9b7f\t{\"Parent\":\"Chrome 34.0 for Android\",\"Platform_Version\":\"4.0\",\"Device_Name\":\"Optimus L9\",\"Device_Maker\":\"LG\",\"Device_Pointing_Method\":\"unknown\",\"Device_Code_Name\":\"P760\",\"Device_Brand_Name\":\"LG\"}",
        "57de16a4e8551c3df52fcbf1458a2d4a\t{\"Parent\":\"Chrome 32.0 for Android\",\"Platform_Version\":\"4.4\",\"Device_Name\":\"Droid Ultra\",\"Device_Maker\":\"Motorola\",\"Device_Code_Name\":\"XT1080\",\"Device_Brand_Name\":\"Motorola\"}",
        "57da892d05d6265cdfab7163107976d3\t{\"Parent\":\"Chrome 31.0 for Android\",\"Platform_Version\":\"4.2\",\"Device_Name\":\"Galaxy Note\",\"Device_Maker\":\"Samsung\",\"Device_Code_Name\":\"GT-N7000\",\"Device_Brand_Name\":\"Samsung\"}",
        "57d04780272f65e0dafcf21076b3f175\t{\"Parent\":\"Chrome 30.0 for Android\",\"Platform_Version\":\"4.3\",\"Device_Name\":\"One S\",\"Device_Maker\":\"HTC\",\"Device_Code_Name\":\"PJ401\",\"Device_Brand_Name\":\"HTC\"}",
        "57d79f45506e9933833e117ef65a6fbc\t{\"Parent\":\"Chrome 17.0 for Android\",\"Platform_Version\":\"2.0\"}",
        "57df65b2194034697d074c8d26397489\t{\"Parent\":\"OneBrowser 3.8\",\"Browser_Bits\":\"32\",\"Platform\":\"iOS\",\"Platform_Version\":\"3.0\",\"Platform_Description\":\"iPod, iPhone \\u0026 iPad\",\"Platform_Bits\":\"32\",\"Platform_Maker\":\"Apple Inc\",\"Device_Name\":\"general Mobile Device\",\"Device_Maker\":\"Apple Inc\",\"Device_Type\":\"Mobile Device\",\"Device_Code_Name\":\"general Mobile Device\",\"Device_Brand_Name\":\"Apple\"}",
        "57d42b09296ee188091a45689c2777dc\t{\"Parent\":\"Playstation\",\"Browser\":\"Sony PSP\",\"isMobileDevice\":true,\"Device_Name\":\"Playstation Portable\",\"Device_Maker\":\"Sony\",\"Device_Type\":\"Console\",\"Device_Code_Name\":\"Playstation Portable\",\"Device_Brand_Name\":\"Sony\"}",
        "57d761bfa8e0af4e0cd7b2f002cf29bc\t{\"Parent\":\"Android Browser 4.0\",\"Platform_Version\":\"2.1\",\"Device_Name\":\"U8100\",\"Device_Maker\":\"Huawei\",\"Device_Pointing_Method\":\"unknown\",\"Device_Code_Name\":\"U8100\",\"Device_Brand_Name\":\"Huawei\"}",
        "57de2114b2ec57661767660bb8e04d6f\t{\"Parent\":\"Opera Mini 25.0\",\"Browser_Bits\":\"32\",\"Platform\":\"Bada\",\"Platform_Version\":\"1.0\",\"Platform_Description\":\"Samsung Bada\",\"Platform_Bits\":\"32\",\"Platform_Maker\":\"Samsung\"}",
        "57d94d9f14f0c79fa0ec23593429cc74\t{\"Parent\":\"iCab 4.1\"}",
        "57de5f03e4bd2a967a4c991bf67beb5e\t{\"Parent\":\"IE 8.0\",\"Browser_Bits\":\"32\",\"Platform\":\"WinXP\",\"Platform_Version\":\"5.1\",\"Platform_Description\":\"Windows XP\",\"Platform_Bits\":\"32\",\"Platform_Maker\":\"Microsoft Corporation\",\"Win32\":true}",
        "57d992d55f848f1120eed962a9f2c54b\t{\"Parent\":\"SeaMonkey 2.10\",\"Browser_Bits\":\"32\",\"Platform\":\"WinVista\",\"Platform_Version\":\"6.0\",\"Platform_Description\":\"Windows Vista\",\"Platform_Bits\":\"64\",\"Platform_Maker\":\"Microsoft Corporation\",\"Win64\":true,\"Device_Name\":\"Windows Desktop\",\"Device_Code_Name\":\"Windows Desktop\"}",
        "57d60af1729316c059b4bea230c87ddb\t{\"Parent\":\"Thunderbird 12.0\",\"Browser_Bits\":\"32\",\"Platform\":\"Win2000\",\"Platform_Version\":\"5.0\",\"Platform_Description\":\"Windows 2000\",\"Platform_Bits\":\"32\",\"Platform_Maker\":\"Microsoft Corporation\",\"Win32\":true,\"Device_Name\":\"Windows Desktop\",\"Device_Code_Name\":\"Windows Desktop\"}",
        "57d276443101727f56a393f3c869af54\t{\"Parent\":\"Firefox 34.0\",\"Browser_Bits\":\"32\",\"Platform\":\"Win10\",\"Platform_Version\":\"10.0\",\"Platform_Description\":\"Windows 10\",\"Platform_Bits\":\"32\",\"Platform_Maker\":\"Microsoft Corporation\",\"Win32\":true,\"Device_Name\":\"Windows Desktop\",\"Device_Code_Name\":\"Windows Desktop\"}",
        "57d1fe7b9c28ee4e1383c1ea4a43b774\t{\"Parent\":\"Firefox 32.0 for Maemo\",\"Device_Name\":\"Atrix\",\"Device_Maker\":\"Motorola\",\"Device_Code_Name\":\"MB860\",\"Device_Brand_Name\":\"Motorola\"}",
        "57d0f0af4b995f2ff73fc036329d483c\t{\"Parent\":\"Firefox 20.0\",\"Browser_Bits\":\"32\",\"Platform\":\"MacOSX\",\"Platform_Version\":\"10.8\",\"Platform_Description\":\"Mac OS X\",\"Platform_Bits\":\"32\",\"Platform_Maker\":\"Apple Inc\",\"Device_Name\":\"Macintosh\",\"Device_Maker\":\"Apple Inc\",\"Device_Code_Name\":\"Macintosh\",\"Device_Brand_Name\":\"Apple\"}",
        "57dbf76966cb80b7e65e027ec6dfb962\t{\"Parent\":\"LG\"}"
    ]
}